stormpy/_version.py
stormpy/__init__.py
stormpy/simulator.py
stormpy/_config.py
stormpy/_core.cpython-314t-darwin.so
stormpy/pycarl/_pycarl_core.cpython-314t-darwin.so
stormpy/pycarl/infinity.py
stormpy/pycarl/_version.py
stormpy/pycarl/__init__.py
stormpy/pycarl/_config.py
stormpy/pycarl/gmp/__init__.py
stormpy/pycarl/gmp/_gmp.cpython-314t-darwin.so
stormpy/pycarl/gmp/parse/__init__.py
stormpy/pycarl/gmp/formula/__init__.py
stormpy/pycarl/gmp/formula/_formula.cpython-314t-darwin.so
stormpy/pycarl/parse/__init__.py
stormpy/pycarl/cln/__init__.py
stormpy/pycarl/cln/_cln.cpython-314t-darwin.so
stormpy/pycarl/cln/parse/__init__.py
stormpy/pycarl/cln/formula/__init__.py
stormpy/pycarl/cln/formula/_formula.cpython-314t-darwin.so
stormpy/pycarl/formula/__init__.py
stormpy/pycarl/formula/_formula.cpython-314t-darwin.so
stormpy/pycarl/convert/cln_converter.py
stormpy/pycarl/convert/__init__.py
stormpy/pycarl/convert/gmp_converter.py
stormpy/dft/__init__.py
stormpy/dft/simulator.py
stormpy/dft/modules.py
stormpy/dft/_dft.cpython-314t-darwin.so
stormpy/logic/__init__.py
stormpy/logic/_logic.cpython-314t-darwin.so
stormpy/gspn/__init__.py
stormpy/gspn/_gspn.cpython-314t-darwin.so
stormpy/exceptions/storm_error.py
stormpy/exceptions/__init__.py
stormpy/storage/__init__.py
stormpy/storage/_storage.cpython-314t-darwin.so
stormpy/.dylibs/libgmpxx.4.dylib
stormpy/.dylibs/libbddx.0.dylib
stormpy/.dylibs/libstorm-parsers.1.11.1.dylib
stormpy/.dylibs/libz3.4.15.3.0.dylib
stormpy/.dylibs/libglpk.40.dylib
stormpy/.dylibs/libxerces-c-3.3.dylib
stormpy/.dylibs/libcarl.14.33.dylib
stormpy/.dylibs/libstorm-version-info.1.11.1.dylib
stormpy/.dylibs/libstorm-conv.1.11.1.dylib
stormpy/.dylibs/libstorm-gspn.1.11.1.dylib
stormpy/.dylibs/libcln.6.dylib
stormpy/.dylibs/libstorm-pomdp.1.11.1.dylib
stormpy/.dylibs/libginac.13.dylib
stormpy/.dylibs/libstorm-pars.1.11.1.dylib
stormpy/.dylibs/libstorm.1.11.1.dylib
stormpy/.dylibs/libspot.0.dylib
stormpy-1.11.3.dist-info/RECORD
stormpy-1.11.3.dist-info/WHEEL
stormpy-1.11.3.dist-info/METADATA
stormpy-1.11.3.dist-info/licenses/LICENSE
