Metadata-Version: 2.2
Name: stormpy
Version: 1.11.3
Summary: stormpy - Python Bindings for Storm
Author-Email: "S. Junges" <sebastian.junges@ru.nl>, "M. Volk" <m.volk@tue.nl>
License:                     GNU GENERAL PUBLIC LICENSE
Classifier: Intended Audience :: Science/Research
Classifier: Topic :: Scientific/Engineering
Classifier: Topic :: Software Development :: Libraries :: Python Modules
Project-URL: Homepage, https://github.com/moves-rwth/stormpy
Project-URL: Documentation, https://moves-rwth.github.io/stormpy
Project-URL: Bug Tracker, https://github.com/moves-rwth/stormpy/issues
Requires-Python: >=3.9
Requires-Dist: Deprecated
Provides-Extra: numpy
Requires-Dist: numpy; extra == "numpy"
Provides-Extra: plot
Requires-Dist: matplotlib; extra == "plot"
Requires-Dist: numpy; extra == "plot"
Requires-Dist: scipy; extra == "plot"
Provides-Extra: doc
Requires-Dist: Sphinx>=8.2.2; extra == "doc"
Requires-Dist: sphinx-nefertiti; extra == "doc"
Requires-Dist: sphinx-copybutton; extra == "doc"
Requires-Dist: nbsphinx; extra == "doc"
Requires-Dist: ipython; extra == "doc"
Requires-Dist: ipykernel; extra == "doc"
Provides-Extra: dev
Requires-Dist: black[jupyter]; extra == "dev"
Provides-Extra: test
Requires-Dist: pytest; extra == "test"
Requires-Dist: nbval; extra == "test"
Requires-Dist: numpy; extra == "test"
